DESCRIPTION.rst
LICENSE
MANIFEST.in
setup.py
pyEnFace/EnphaseInterface.py
pyEnFace/EnvoyInterface.py
pyEnFace/__init__.py
pyEnFace.egg-info/PKG-INFO
pyEnFace.egg-info/SOURCES.txt
pyEnFace.egg-info/dependency_links.txt
pyEnFace.egg-info/requires.txt
pyEnFace.egg-info/top_level.txt