Metadata-Version: 1.1
Name: pyEnFace
Version: 0.9.7
Summary: A python interface to the Enphase Developer API
Home-page: https://github.com/e2thenegpii/EnphaseInterface
Author: Eldon Allred
Author-email: e2thenegpii@gmail.com
License: Gnu Public License version 3
Keywords: enphase development
Platform: UNKNOWN
Classifier: Development Status :: 3 - Alpha
Classifier: Intended Audience :: Developers
Classifier: License :: OSI Approved :: GNU General Public License v3 (GPLv3)
Classifier: Programming Language :: Python :: 3.4
Classifier: Topic :: Software Development :: Libraries :: Python Modules
